odoo/addons/web_responsive/README.rst
odoo/addons/web_responsive/__init__.py
odoo/addons/web_responsive/__manifest__.py
odoo/addons/web_responsive/i18n/ca.po
odoo/addons/web_responsive/i18n/da.po
odoo/addons/web_responsive/i18n/de.po
odoo/addons/web_responsive/i18n/es.po
odoo/addons/web_responsive/i18n/hr.po
odoo/addons/web_responsive/i18n/pt_BR.po
odoo/addons/web_responsive/i18n/web_responsive.pot
odoo/addons/web_responsive/models/__init__.py
odoo/addons/web_responsive/models/inherited_res_users.py
odoo/addons/web_responsive/readme/CONTRIBUTORS.rst
odoo/addons/web_responsive/readme/DESCRIPTION.rst
odoo/addons/web_responsive/readme/ROADMAP.rst
odoo/addons/web_responsive/readme/USAGE.rst
odoo/addons/web_responsive/static/description/icon.png
odoo/addons/web_responsive/static/description/index.html
odoo/addons/web_responsive/static/lib/css/drawer.3.2.2.css
odoo/addons/web_responsive/static/lib/js/bililiteRange.2.6.js
odoo/addons/web_responsive/static/lib/js/drawer.3.2.2.js
odoo/addons/web_responsive/static/lib/js/iscroll-probe.5.2.0.js
odoo/addons/web_responsive/static/lib/js/jquery.sendkeys.4.js
odoo/addons/web_responsive/static/src/js/web_responsive.js
odoo/addons/web_responsive/static/src/less/app_drawer.less
odoo/addons/web_responsive/static/src/less/form_view.less
odoo/addons/web_responsive/static/src/less/main.less
odoo/addons/web_responsive/static/src/less/navbar.less
odoo/addons/web_responsive/static/src/less/variables.less
odoo/addons/web_responsive/static/src/xml/app_drawer_menu_search.xml
odoo/addons/web_responsive/static/src/xml/form_view.xml
odoo/addons/web_responsive/static/src/xml/navbar.xml
odoo/addons/web_responsive/static/tests/js/web_responsive.js
odoo/addons/web_responsive/tests/__init__.py
odoo/addons/web_responsive/tests/test_res_users.py
odoo/addons/web_responsive/tests/test_ui.py
odoo/addons/web_responsive/views/assets.xml
odoo/addons/web_responsive/views/inherited_view_users_form_simple_modif.xml
odoo11_addon_web_responsive-11.0.2.0.3.dist-info/METADATA
odoo11_addon_web_responsive-11.0.2.0.3.dist-info/RECORD
odoo11_addon_web_responsive-11.0.2.0.3.dist-info/WHEEL
odoo11_addon_web_responsive-11.0.2.0.3.dist-info/top_level.txt
